{"config":{"output_file":null,"full_docs":false,"pub_only":false,"reachable_only":false,"distro_crate":false,"signatures":false,"borrow_data":false},"version":"0.19.1","compilation":{"directory":"c:\\Projetos\\StraightEquation","program":"C:\\Users\\marco\\.rustup\\toolchains\\stable-x86_64-pc-windows-msvc\\bin\\rls.exe","arguments":[],"output":"c:\\Projetos\\StraightEquation\\target\\rls\\debug\\deps\\libstraight_equation-ad080e4af9d5b8f7.rmeta"},"prelude":{"crate_id":{"name":"straight_equation","disambiguator":[7474747147433145579,15869268867080653175]},"crate_root":"src","external_crates":[{"file_name":"c:\\Projetos\\StraightEquation\\src\\main.rs","num":1,"id":{"name":"std","disambiguator":[902711862199739234,15082167224296373374]}},{"file_name":"c:\\Projetos\\StraightEquation\\src\\main.rs","num":2,"id":{"name":"core","disambiguator":[5048311760381386034,12753961808535803278]}},{"file_name":"c:\\Projetos\\StraightEquation\\src\\main.rs","num":3,"id":{"name":"compiler_builtins","disambiguator":[847775214756591688,12437863933651081164]}},{"file_name":"c:\\Projetos\\StraightEquation\\src\\main.rs","num":4,"id":{"name":"rustc_std_workspace_core","disambiguator":[18098153966720408130,4102567439342721650]}},{"file_name":"c:\\Projetos\\StraightEquation\\src\\main.rs","num":5,"id":{"name":"alloc","disambiguator":[14085577876822856882,15393158987199036233]}},{"file_name":"c:\\Projetos\\StraightEquation\\src\\main.rs","num":6,"id":{"name":"libc","disambiguator":[3188366355873518403,14471389999965490426]}},{"file_name":"c:\\Projetos\\StraightEquation\\src\\main.rs","num":7,"id":{"name":"unwind","disambiguator":[10237517513868340142,18396708545822173986]}},{"file_name":"c:\\Projetos\\StraightEquation\\src\\main.rs","num":8,"id":{"name":"cfg_if","disambiguator":[17305999185247584930,14125623615750666193]}},{"file_name":"c:\\Projetos\\StraightEquation\\src\\main.rs","num":9,"id":{"name":"hashbrown","disambiguator":[7451980452763147359,4800032867518142595]}},{"file_name":"c:\\Projetos\\StraightEquation\\src\\main.rs","num":10,"id":{"name":"rustc_std_workspace_alloc","disambiguator":[842541340887862638,17591716377464122790]}},{"file_name":"c:\\Projetos\\StraightEquation\\src\\main.rs","num":11,"id":{"name":"rustc_demangle","disambiguator":[14650435931294811010,18006816567319070280]}},{"file_name":"c:\\Projetos\\StraightEquation\\src\\main.rs","num":12,"id":{"name":"std_detect","disambiguator":[16073749092757737146,5785406473963590530]}},{"file_name":"c:\\Projetos\\StraightEquation\\src\\main.rs","num":13,"id":{"name":"panic_unwind","disambiguator":[9426002052484834533,14451905897035318657]}}],"span":{"file_name":"src\\main.rs","byte_start":0,"byte_end":1766,"line_start":1,"line_end":63,"column_start":1,"column_end":2}},"imports":[],"defs":[{"kind":"Mod","id":{"krate":0,"index":0},"span":{"file_name":"src\\main.rs","byte_start":0,"byte_end":1766,"line_start":1,"line_end":63,"column_start":1,"column_end":2},"name":"","qualname":"::","value":"src\\main.rs","parent":null,"children":[{"krate":0,"index":1},{"krate":0,"index":2},{"krate":0,"index":3},{"krate":0,"index":4},{"krate":0,"index":5},{"krate":0,"index":6},{"krate":0,"index":7},{"krate":0,"index":8},{"krate":0,"index":9},{"krate":0,"index":10}],"decl_id":null,"docs":"","sig":null,"attributes":[]},{"kind":"Local","id":{"krate":0,"index":1073741827},"span":{"file_name":"src\\main.rs","byte_start":31,"byte_end":33,"line_start":1,"line_end":1,"column_start":32,"column_end":34},"name":"xa","qualname":"::constant_coeficient_general::xa","value":"f64","parent":null,"children":[],"decl_id":null,"docs":"","sig":null,"attributes":[]},{"kind":"Local","id":{"krate":0,"index":536870915},"span":{"file_name":"src\\main.rs","byte_start":39,"byte_end":41,"line_start":1,"line_end":1,"column_start":40,"column_end":42},"name":"ya","qualname":"::constant_coeficient_general::ya","value":"f64","parent":null,"children":[],"decl_id":null,"docs":"","sig":null,"attributes":[]},{"kind":"Local","id":{"krate":0,"index":1610612739},"span":{"file_name":"src\\main.rs","byte_start":47,"byte_end":49,"line_start":1,"line_end":1,"column_start":48,"column_end":50},"name":"xb","qualname":"::constant_coeficient_general::xb","value":"f64","parent":null,"children":[],"decl_id":null,"docs":"","sig":null,"attributes":[]},{"kind":"Local","id":{"krate":0,"index":268435459},"span":{"file_name":"src\\main.rs","byte_start":55,"byte_end":57,"line_start":1,"line_end":1,"column_start":56,"column_end":58},"name":"yb","qualname":"::constant_coeficient_general::yb","value":"f64","parent":null,"children":[],"decl_id":null,"docs":"","sig":null,"attributes":[]},{"kind":"Function","id":{"krate":0,"index":3},"span":{"file_name":"src\\main.rs","byte_start":3,"byte_end":30,"line_start":1,"line_end":1,"column_start":4,"column_end":31},"name":"constant_coeficient_general","qualname":"::constant_coeficient_general","value":"fn constant_coeficient_general(f64, f64, f64, f64)","parent":null,"children":[],"decl_id":null,"docs":"","sig":null,"attributes":[]},{"kind":"Local","id":{"krate":0,"index":1073741828},"span":{"file_name":"src\\main.rs","byte_start":97,"byte_end":99,"line_start":5,"line_end":5,"column_start":30,"column_end":32},"name":"xa","qualname":"::linear_coeficient_general::xa","value":"f64","parent":null,"children":[],"decl_id":null,"docs":"","sig":null,"attributes":[]},{"kind":"Local","id":{"krate":0,"index":536870916},"span":{"file_name":"src\\main.rs","byte_start":105,"byte_end":107,"line_start":5,"line_end":5,"column_start":38,"column_end":40},"name":"ya","qualname":"::linear_coeficient_general::ya","value":"f64","parent":null,"children":[],"decl_id":null,"docs":"","sig":null,"attributes":[]},{"kind":"Local","id":{"krate":0,"index":1610612740},"span":{"file_name":"src\\main.rs","byte_start":113,"byte_end":115,"line_start":5,"line_end":5,"column_start":46,"column_end":48},"name":"xb","qualname":"::linear_coeficient_general::xb","value":"f64","parent":null,"children":[],"decl_id":null,"docs":"","sig":null,"attributes":[]},{"kind":"Local","id":{"krate":0,"index":268435460},"span":{"file_name":"src\\main.rs","byte_start":121,"byte_end":123,"line_start":5,"line_end":5,"column_start":54,"column_end":56},"name":"yb","qualname":"::linear_coeficient_general::yb","value":"f64","parent":null,"children":[],"decl_id":null,"docs":"","sig":null,"attributes":[]},{"kind":"Function","id":{"krate":0,"index":4},"span":{"file_name":"src\\main.rs","byte_start":71,"byte_end":96,"line_start":5,"line_end":5,"column_start":4,"column_end":29},"name":"linear_coeficient_general","qualname":"::linear_coeficient_general","value":"fn linear_coeficient_general(f64, f64, f64, f64)","parent":null,"children":[],"decl_id":null,"docs":"","sig":null,"attributes":[]},{"kind":"Local","id":{"krate":0,"index":1073741829},"span":{"file_name":"src\\main.rs","byte_start":164,"byte_end":166,"line_start":9,"line_end":9,"column_start":31,"column_end":33},"name":"xa","qualname":"::angular_coeficient_general::xa","value":"f64","parent":null,"children":[],"decl_id":null,"docs":"","sig":null,"attributes":[]},{"kind":"Local","id":{"krate":0,"index":536870917},"span":{"file_name":"src\\main.rs","byte_start":172,"byte_end":174,"line_start":9,"line_end":9,"column_start":39,"column_end":41},"name":"ya","qualname":"::angular_coeficient_general::ya","value":"f64","parent":null,"children":[],"decl_id":null,"docs":"","sig":null,"attributes":[]},{"kind":"Local","id":{"krate":0,"index":1610612741},"span":{"file_name":"src\\main.rs","byte_start":180,"byte_end":182,"line_start":9,"line_end":9,"column_start":47,"column_end":49},"name":"xb","qualname":"::angular_coeficient_general::xb","value":"f64","parent":null,"children":[],"decl_id":null,"docs":"","sig":null,"attributes":[]},{"kind":"Local","id":{"krate":0,"index":268435461},"span":{"file_name":"src\\main.rs","byte_start":188,"byte_end":190,"line_start":9,"line_end":9,"column_start":55,"column_end":57},"name":"yb","qualname":"::angular_coeficient_general::yb","value":"f64","parent":null,"children":[],"decl_id":null,"docs":"","sig":null,"attributes":[]},{"kind":"Function","id":{"krate":0,"index":5},"span":{"file_name":"src\\main.rs","byte_start":137,"byte_end":163,"line_start":9,"line_end":9,"column_start":4,"column_end":30},"name":"angular_coeficient_general","qualname":"::angular_coeficient_general","value":"fn angular_coeficient_general(f64, f64, f64, f64)","parent":null,"children":[],"decl_id":null,"docs":"","sig":null,"attributes":[]},{"kind":"Local","id":{"krate":0,"index":1073741830},"span":{"file_name":"src\\main.rs","byte_start":221,"byte_end":223,"line_start":13,"line_end":13,"column_start":21,"column_end":23},"name":"xa","qualname":"::general_equation::xa","value":"f64","parent":null,"children":[],"decl_id":null,"docs":"","sig":null,"attributes":[]},{"kind":"Local","id":{"krate":0,"index":536870918},"span":{"file_name":"src\\main.rs","byte_start":229,"byte_end":231,"line_start":13,"line_end":13,"column_start":29,"column_end":31},"name":"ya","qualname":"::general_equation::ya","value":"f64","parent":null,"children":[],"decl_id":null,"docs":"","sig":null,"attributes":[]},{"kind":"Local","id":{"krate":0,"index":1610612742},"span":{"file_name":"src\\main.rs","byte_start":237,"byte_end":239,"line_start":13,"line_end":13,"column_start":37,"column_end":39},"name":"xb","qualname":"::general_equation::xb","value":"f64","parent":null,"children":[],"decl_id":null,"docs":"","sig":null,"attributes":[]},{"kind":"Local","id":{"krate":0,"index":268435462},"span":{"file_name":"src\\main.rs","byte_start":245,"byte_end":247,"line_start":13,"line_end":13,"column_start":45,"column_end":47},"name":"yb","qualname":"::general_equation::yb","value":"f64","parent":null,"children":[],"decl_id":null,"docs":"","sig":null,"attributes":[]},{"kind":"Function","id":{"krate":0,"index":6},"span":{"file_name":"src\\main.rs","byte_start":204,"byte_end":220,"line_start":13,"line_end":13,"column_start":4,"column_end":20},"name":"general_equation","qualname":"::general_equation","value":"fn general_equation(f64, f64, f64, f64)","parent":null,"children":[],"decl_id":null,"docs":"","sig":null,"attributes":[]},{"kind":"Local","id":{"krate":0,"index":1744830470},"span":{"file_name":"src\\main.rs","byte_start":262,"byte_end":281,"line_start":14,"line_end":14,"column_start":9,"column_end":28},"name":"_angular_coeficient","qualname":"_angular_coeficient$HirId { owner: DefId(0:6 ~ straight_equation[67bb]::general_equation), local_id: 22 }","value":"()","parent":null,"children":[],"decl_id":null,"docs":"","sig":null,"attributes":[]},{"kind":"Local","id":{"krate":0,"index":2751463430},"span":{"file_name":"src\\main.rs","byte_start":340,"byte_end":358,"line_start":15,"line_end":15,"column_start":9,"column_end":27},"name":"_linear_coeficient","qualname":"_linear_coeficient$HirId { owner: DefId(0:6 ~ straight_equation[67bb]::general_equation), local_id: 37 }","value":"()","parent":null,"children":[],"decl_id":null,"docs":"","sig":null,"attributes":[]},{"kind":"Local","id":{"krate":0,"index":738197510},"span":{"file_name":"src\\main.rs","byte_start":416,"byte_end":436,"line_start":16,"line_end":16,"column_start":9,"column_end":29},"name":"_constant_coeficient","qualname":"_constant_coeficient$HirId { owner: DefId(0:6 ~ straight_equation[67bb]::general_equation), local_id: 52 }","value":"()","parent":null,"children":[],"decl_id":null,"docs":"","sig":null,"attributes":[]},{"kind":"Local","id":{"krate":0,"index":1073741831},"span":{"file_name":"src\\main.rs","byte_start":518,"byte_end":520,"line_start":19,"line_end":19,"column_start":30,"column_end":32},"name":"xa","qualname":"::linear_coeficient_reduced::xa","value":"f64","parent":null,"children":[],"decl_id":null,"docs":"","sig":null,"attributes":[]},{"kind":"Local","id":{"krate":0,"index":536870919},"span":{"file_name":"src\\main.rs","byte_start":526,"byte_end":528,"line_start":19,"line_end":19,"column_start":38,"column_end":40},"name":"ya","qualname":"::linear_coeficient_reduced::ya","value":"f64","parent":null,"children":[],"decl_id":null,"docs":"","sig":null,"attributes":[]},{"kind":"Local","id":{"krate":0,"index":1610612743},"span":{"file_name":"src\\main.rs","byte_start":534,"byte_end":536,"line_start":19,"line_end":19,"column_start":46,"column_end":48},"name":"xb","qualname":"::linear_coeficient_reduced::xb","value":"f64","parent":null,"children":[],"decl_id":null,"docs":"","sig":null,"attributes":[]},{"kind":"Local","id":{"krate":0,"index":268435463},"span":{"file_name":"src\\main.rs","byte_start":542,"byte_end":544,"line_start":19,"line_end":19,"column_start":54,"column_end":56},"name":"yb","qualname":"::linear_coeficient_reduced::yb","value":"f64","parent":null,"children":[],"decl_id":null,"docs":"","sig":null,"attributes":[]},{"kind":"Function","id":{"krate":0,"index":7},"span":{"file_name":"src\\main.rs","byte_start":492,"byte_end":517,"line_start":19,"line_end":19,"column_start":4,"column_end":29},"name":"linear_coeficient_reduced","qualname":"::linear_coeficient_reduced","value":"fn linear_coeficient_reduced(f64, f64, f64, f64)","parent":null,"children":[],"decl_id":null,"docs":"","sig":null,"attributes":[]},{"kind":"Local","id":{"krate":0,"index":2281701383},"span":{"file_name":"src\\main.rs","byte_start":559,"byte_end":564,"line_start":20,"line_end":20,"column_start":9,"column_end":14},"name":"yb_ya","qualname":"yb_ya$HirId { owner: DefId(0:7 ~ straight_equation[67bb]::linear_coeficient_reduced), local_id: 17 }","value":"f64","parent":null,"children":[],"decl_id":null,"docs":"","sig":null,"attributes":[]},{"kind":"Local","id":{"krate":0,"index":3623878663},"span":{"file_name":"src\\main.rs","byte_start":588,"byte_end":593,"line_start":21,"line_end":21,"column_start":9,"column_end":14},"name":"xb_xa","qualname":"xb_xa$HirId { owner: DefId(0:7 ~ straight_equation[67bb]::linear_coeficient_reduced), local_id: 27 }","value":"f64","parent":null,"children":[],"decl_id":null,"docs":"","sig":null,"attributes":[]},{"kind":"Local","id":{"krate":0,"index":2751463431},"span":{"file_name":"src\\main.rs","byte_start":617,"byte_end":635,"line_start":22,"line_end":22,"column_start":9,"column_end":27},"name":"angular_coeficient","qualname":"angular_coeficient$HirId { owner: DefId(0:7 ~ straight_equation[67bb]::linear_coeficient_reduced), local_id: 37 }","value":"f64","parent":null,"children":[],"decl_id":null,"docs":"","sig":null,"attributes":[]},{"kind":"Local","id":{"krate":0,"index":3019898887},"span":{"file_name":"src\\main.rs","byte_start":669,"byte_end":686,"line_start":23,"line_end":23,"column_start":13,"column_end":30},"name":"linear_coeficient","qualname":"linear_coeficient$HirId { owner: DefId(0:7 ~ straight_equation[67bb]::linear_coeficient_reduced), local_id: 45 }","value":"f64","parent":null,"children":[],"decl_id":null,"docs":"","sig":null,"attributes":[]},{"kind":"Local","id":{"krate":0,"index":3690987527},"span":{"file_name":"src\\main.rs","byte_start":774,"byte_end":779,"line_start":25,"line_end":25,"column_start":13,"column_end":18},"name":"value","qualname":"value$HirId { owner: DefId(0:7 ~ straight_equation[67bb]::linear_coeficient_reduced), local_id: 59 }","value":"std::string::String","parent":null,"children":[],"decl_id":null,"docs":"","sig":null,"attributes":[]},{"kind":"Local","id":{"krate":0,"index":1073741832},"span":{"file_name":"src\\main.rs","byte_start":987,"byte_end":989,"line_start":36,"line_end":36,"column_start":31,"column_end":33},"name":"xa","qualname":"::angular_coeficient_reduced::xa","value":"f64","parent":null,"children":[],"decl_id":null,"docs":"","sig":null,"attributes":[]},{"kind":"Local","id":{"krate":0,"index":536870920},"span":{"file_name":"src\\main.rs","byte_start":995,"byte_end":997,"line_start":36,"line_end":36,"column_start":39,"column_end":41},"name":"ya","qualname":"::angular_coeficient_reduced::ya","value":"f64","parent":null,"children":[],"decl_id":null,"docs":"","sig":null,"attributes":[]},{"kind":"Local","id":{"krate":0,"index":1610612744},"span":{"file_name":"src\\main.rs","byte_start":1003,"byte_end":1005,"line_start":36,"line_end":36,"column_start":47,"column_end":49},"name":"xb","qualname":"::angular_coeficient_reduced::xb","value":"f64","parent":null,"children":[],"decl_id":null,"docs":"","sig":null,"attributes":[]},{"kind":"Local","id":{"krate":0,"index":268435464},"span":{"file_name":"src\\main.rs","byte_start":1011,"byte_end":1013,"line_start":36,"line_end":36,"column_start":55,"column_end":57},"name":"yb","qualname":"::angular_coeficient_reduced::yb","value":"f64","parent":null,"children":[],"decl_id":null,"docs":"","sig":null,"attributes":[]},{"kind":"Function","id":{"krate":0,"index":8},"span":{"file_name":"src\\main.rs","byte_start":960,"byte_end":986,"line_start":36,"line_end":36,"column_start":4,"column_end":30},"name":"angular_coeficient_reduced","qualname":"::angular_coeficient_reduced","value":"fn angular_coeficient_reduced(f64, f64, f64, f64)","parent":null,"children":[],"decl_id":null,"docs":"","sig":null,"attributes":[]},{"kind":"Local","id":{"krate":0,"index":2281701384},"span":{"file_name":"src\\main.rs","byte_start":1028,"byte_end":1033,"line_start":37,"line_end":37,"column_start":9,"column_end":14},"name":"yb_ya","qualname":"yb_ya$HirId { owner: DefId(0:8 ~ straight_equation[67bb]::angular_coeficient_reduced), local_id: 17 }","value":"f64","parent":null,"children":[],"decl_id":null,"docs":"","sig":null,"attributes":[]},{"kind":"Local","id":{"krate":0,"index":3623878664},"span":{"file_name":"src\\main.rs","byte_start":1057,"byte_end":1062,"line_start":38,"line_end":38,"column_start":9,"column_end":14},"name":"xb_xa","qualname":"xb_xa$HirId { owner: DefId(0:8 ~ straight_equation[67bb]::angular_coeficient_reduced), local_id: 27 }","value":"f64","parent":null,"children":[],"decl_id":null,"docs":"","sig":null,"attributes":[]},{"kind":"Local","id":{"krate":0,"index":2751463432},"span":{"file_name":"src\\main.rs","byte_start":1086,"byte_end":1104,"line_start":39,"line_end":39,"column_start":9,"column_end":27},"name":"angular_coeficient","qualname":"angular_coeficient$HirId { owner: DefId(0:8 ~ straight_equation[67bb]::angular_coeficient_reduced), local_id: 37 }","value":"f64","parent":null,"children":[],"decl_id":null,"docs":"","sig":null,"attributes":[]},{"kind":"Local","id":{"krate":0,"index":1409286152},"span":{"file_name":"src\\main.rs","byte_start":1138,"byte_end":1143,"line_start":40,"line_end":40,"column_start":13,"column_end":18},"name":"value","qualname":"value$HirId { owner: DefId(0:8 ~ straight_equation[67bb]::angular_coeficient_reduced), local_id: 42 }","value":"std::string::String","parent":null,"children":[],"decl_id":null,"docs":"","sig":null,"attributes":[]},{"kind":"Local","id":{"krate":0,"index":1073741833},"span":{"file_name":"src\\main.rs","byte_start":1343,"byte_end":1345,"line_start":51,"line_end":51,"column_start":21,"column_end":23},"name":"xa","qualname":"::reduced_equation::xa","value":"f64","parent":null,"children":[],"decl_id":null,"docs":"","sig":null,"attributes":[]},{"kind":"Local","id":{"krate":0,"index":536870921},"span":{"file_name":"src\\main.rs","byte_start":1351,"byte_end":1353,"line_start":51,"line_end":51,"column_start":29,"column_end":31},"name":"ya","qualname":"::reduced_equation::ya","value":"f64","parent":null,"children":[],"decl_id":null,"docs":"","sig":null,"attributes":[]},{"kind":"Local","id":{"krate":0,"index":1610612745},"span":{"file_name":"src\\main.rs","byte_start":1359,"byte_end":1361,"line_start":51,"line_end":51,"column_start":37,"column_end":39},"name":"xb","qualname":"::reduced_equation::xb","value":"f64","parent":null,"children":[],"decl_id":null,"docs":"","sig":null,"attributes":[]},{"kind":"Local","id":{"krate":0,"index":268435465},"span":{"file_name":"src\\main.rs","byte_start":1367,"byte_end":1369,"line_start":51,"line_end":51,"column_start":45,"column_end":47},"name":"yb","qualname":"::reduced_equation::yb","value":"f64","parent":null,"children":[],"decl_id":null,"docs":"","sig":null,"attributes":[]},{"kind":"Function","id":{"krate":0,"index":9},"span":{"file_name":"src\\main.rs","byte_start":1326,"byte_end":1342,"line_start":51,"line_end":51,"column_start":4,"column_end":20},"name":"reduced_equation","qualname":"::reduced_equation","value":"fn reduced_equation(f64, f64, f64, f64)","parent":null,"children":[],"decl_id":null,"docs":"","sig":null,"attributes":[]},{"kind":"Local","id":{"krate":0,"index":1744830473},"span":{"file_name":"src\\main.rs","byte_start":1384,"byte_end":1403,"line_start":52,"line_end":52,"column_start":9,"column_end":28},"name":"_angular_coeficient","qualname":"_angular_coeficient$HirId { owner: DefId(0:9 ~ straight_equation[67bb]::reduced_equation), local_id: 22 }","value":"()","parent":null,"children":[],"decl_id":null,"docs":"","sig":null,"attributes":[]},{"kind":"Local","id":{"krate":0,"index":2751463433},"span":{"file_name":"src\\main.rs","byte_start":1462,"byte_end":1480,"line_start":53,"line_end":53,"column_start":9,"column_end":27},"name":"_linear_coeficient","qualname":"_linear_coeficient$HirId { owner: DefId(0:9 ~ straight_equation[67bb]::reduced_equation), local_id: 37 }","value":"()","parent":null,"children":[],"decl_id":null,"docs":"","sig":null,"attributes":[]},{"kind":"Function","id":{"krate":0,"index":10},"span":{"file_name":"src\\main.rs","byte_start":1536,"byte_end":1540,"line_start":56,"line_end":56,"column_start":4,"column_end":8},"name":"main","qualname":"::main","value":"fn main()","parent":null,"children":[],"decl_id":null,"docs":"","sig":null,"attributes":[]},{"kind":"Local","id":{"krate":0,"index":2684354570},"span":{"file_name":"src\\main.rs","byte_start":1553,"byte_end":1555,"line_start":57,"line_end":57,"column_start":9,"column_end":11},"name":"xa","qualname":"xa$HirId { owner: DefId(0:10 ~ straight_equation[67bb]::main), local_id: 5 }","value":"f64","parent":null,"children":[],"decl_id":null,"docs":"","sig":null,"attributes":[]},{"kind":"Local","id":{"krate":0,"index":3489660938},"span":{"file_name":"src\\main.rs","byte_start":1575,"byte_end":1577,"line_start":58,"line_end":58,"column_start":9,"column_end":11},"name":"ya","qualname":"ya$HirId { owner: DefId(0:10 ~ straight_equation[67bb]::main), local_id: 11 }","value":"f64","parent":null,"children":[],"decl_id":null,"docs":"","sig":null,"attributes":[]},{"kind":"Local","id":{"krate":0,"index":2281701386},"span":{"file_name":"src\\main.rs","byte_start":1597,"byte_end":1599,"line_start":59,"line_end":59,"column_start":9,"column_end":11},"name":"xb","qualname":"xb$HirId { owner: DefId(0:10 ~ straight_equation[67bb]::main), local_id: 17 }","value":"f64","parent":null,"children":[],"decl_id":null,"docs":"","sig":null,"attributes":[]},{"kind":"Local","id":{"krate":0,"index":3892314122},"span":{"file_name":"src\\main.rs","byte_start":1619,"byte_end":1621,"line_start":60,"line_end":60,"column_start":9,"column_end":11},"name":"yb","qualname":"yb$HirId { owner: DefId(0:10 ~ straight_equation[67bb]::main), local_id: 23 }","value":"f64","parent":null,"children":[],"decl_id":null,"docs":"","sig":null,"attributes":[]},{"kind":"Local","id":{"krate":0,"index":1677721610},"span":{"file_name":"src\\main.rs","byte_start":1641,"byte_end":1658,"line_start":61,"line_end":61,"column_start":9,"column_end":26},"name":"_reduced_equation","qualname":"_reduced_equation$HirId { owner: DefId(0:10 ~ straight_equation[67bb]::main), local_id: 38 }","value":"()","parent":null,"children":[],"decl_id":null,"docs":"","sig":null,"attributes":[]},{"kind":"Local","id":{"krate":0,"index":2885681162},"span":{"file_name":"src\\main.rs","byte_start":1707,"byte_end":1724,"line_start":62,"line_end":62,"column_start":9,"column_end":26},"name":"_general_equation","qualname":"_general_equation$HirId { owner: DefId(0:10 ~ straight_equation[67bb]::main), local_id: 53 }","value":"()","parent":null,"children":[],"decl_id":null,"docs":"","sig":null,"attributes":[]}],"impls":[],"refs":[{"kind":"Function","span":{"file_name":"src\\main.rs","byte_start":288,"byte_end":314,"line_start":14,"line_end":14,"column_start":35,"column_end":61},"ref_id":{"krate":0,"index":5}},{"kind":"Variable","span":{"file_name":"src\\main.rs","byte_start":315,"byte_end":317,"line_start":14,"line_end":14,"column_start":62,"column_end":64},"ref_id":{"krate":0,"index":1073741830}},{"kind":"Variable","span":{"file_name":"src\\main.rs","byte_start":319,"byte_end":321,"line_start":14,"line_end":14,"column_start":66,"column_end":68},"ref_id":{"krate":0,"index":536870918}},{"kind":"Variable","span":{"file_name":"src\\main.rs","byte_start":323,"byte_end":325,"line_start":14,"line_end":14,"column_start":70,"column_end":72},"ref_id":{"krate":0,"index":1610612742}},{"kind":"Variable","span":{"file_name":"src\\main.rs","byte_start":327,"byte_end":329,"line_start":14,"line_end":14,"column_start":74,"column_end":76},"ref_id":{"krate":0,"index":268435462}},{"kind":"Function","span":{"file_name":"src\\main.rs","byte_start":365,"byte_end":390,"line_start":15,"line_end":15,"column_start":34,"column_end":59},"ref_id":{"krate":0,"index":4}},{"kind":"Variable","span":{"file_name":"src\\main.rs","byte_start":391,"byte_end":393,"line_start":15,"line_end":15,"column_start":60,"column_end":62},"ref_id":{"krate":0,"index":1073741830}},{"kind":"Variable","span":{"file_name":"src\\main.rs","byte_start":395,"byte_end":397,"line_start":15,"line_end":15,"column_start":64,"column_end":66},"ref_id":{"krate":0,"index":536870918}},{"kind":"Variable","span":{"file_name":"src\\main.rs","byte_start":399,"byte_end":401,"line_start":15,"line_end":15,"column_start":68,"column_end":70},"ref_id":{"krate":0,"index":1610612742}},{"kind":"Variable","span":{"file_name":"src\\main.rs","byte_start":403,"byte_end":405,"line_start":15,"line_end":15,"column_start":72,"column_end":74},"ref_id":{"krate":0,"index":268435462}},{"kind":"Function","span":{"file_name":"src\\main.rs","byte_start":443,"byte_end":468,"line_start":16,"line_end":16,"column_start":36,"column_end":61},"ref_id":{"krate":0,"index":4}},{"kind":"Variable","span":{"file_name":"src\\main.rs","byte_start":469,"byte_end":471,"line_start":16,"line_end":16,"column_start":62,"column_end":64},"ref_id":{"krate":0,"index":1073741830}},{"kind":"Variable","span":{"file_name":"src\\main.rs","byte_start":473,"byte_end":475,"line_start":16,"line_end":16,"column_start":66,"column_end":68},"ref_id":{"krate":0,"index":536870918}},{"kind":"Variable","span":{"file_name":"src\\main.rs","byte_start":477,"byte_end":479,"line_start":16,"line_end":16,"column_start":70,"column_end":72},"ref_id":{"krate":0,"index":1610612742}},{"kind":"Variable","span":{"file_name":"src\\main.rs","byte_start":481,"byte_end":483,"line_start":16,"line_end":16,"column_start":74,"column_end":76},"ref_id":{"krate":0,"index":268435462}},{"kind":"Variable","span":{"file_name":"src\\main.rs","byte_start":571,"byte_end":573,"line_start":20,"line_end":20,"column_start":21,"column_end":23},"ref_id":{"krate":0,"index":268435463}},{"kind":"Variable","span":{"file_name":"src\\main.rs","byte_start":576,"byte_end":578,"line_start":20,"line_end":20,"column_start":26,"column_end":28},"ref_id":{"krate":0,"index":536870919}},{"kind":"Variable","span":{"file_name":"src\\main.rs","byte_start":600,"byte_end":602,"line_start":21,"line_end":21,"column_start":21,"column_end":23},"ref_id":{"krate":0,"index":1610612743}},{"kind":"Variable","span":{"file_name":"src\\main.rs","byte_start":605,"byte_end":607,"line_start":21,"line_end":21,"column_start":26,"column_end":28},"ref_id":{"krate":0,"index":1073741831}},{"kind":"Variable","span":{"file_name":"src\\main.rs","byte_start":642,"byte_end":647,"line_start":22,"line_end":22,"column_start":34,"column_end":39},"ref_id":{"krate":0,"index":2281701383}},{"kind":"Variable","span":{"file_name":"src\\main.rs","byte_start":650,"byte_end":655,"line_start":22,"line_end":22,"column_start":42,"column_end":47},"ref_id":{"krate":0,"index":3623878663}},{"kind":"Variable","span":{"file_name":"src\\main.rs","byte_start":689,"byte_end":707,"line_start":23,"line_end":23,"column_start":33,"column_end":51},"ref_id":{"krate":0,"index":2751463431}},{"kind":"Variable","span":{"file_name":"src\\main.rs","byte_start":710,"byte_end":712,"line_start":23,"line_end":23,"column_start":54,"column_end":56},"ref_id":{"krate":0,"index":1073741831}},{"kind":"Variable","span":{"file_name":"src\\main.rs","byte_start":738,"byte_end":755,"line_start":24,"line_end":24,"column_start":25,"column_end":42},"ref_id":{"krate":0,"index":3019898887}},{"kind":"Variable","span":{"file_name":"src\\main.rs","byte_start":758,"byte_end":760,"line_start":24,"line_end":24,"column_start":45,"column_end":47},"ref_id":{"krate":0,"index":536870919}},{"kind":"Variable","span":{"file_name":"src\\main.rs","byte_start":718,"byte_end":735,"line_start":24,"line_end":24,"column_start":5,"column_end":22},"ref_id":{"krate":0,"index":3019898887}},{"kind":"Type","span":{"file_name":"src\\main.rs","byte_start":781,"byte_end":787,"line_start":25,"line_end":25,"column_start":20,"column_end":26},"ref_id":{"krate":5,"index":7286}},{"kind":"Variable","span":{"file_name":"src\\main.rs","byte_start":796,"byte_end":813,"line_start":26,"line_end":26,"column_start":8,"column_end":25},"ref_id":{"krate":0,"index":3019898887}},{"kind":"Variable","span":{"file_name":"src\\main.rs","byte_start":829,"byte_end":834,"line_start":27,"line_end":27,"column_start":9,"column_end":14},"ref_id":{"krate":0,"index":3690987527}},{"kind":"Variable","span":{"file_name":"src\\main.rs","byte_start":854,"byte_end":871,"line_start":28,"line_end":28,"column_start":14,"column_end":31},"ref_id":{"krate":0,"index":3019898887}},{"kind":"Variable","span":{"file_name":"src\\main.rs","byte_start":887,"byte_end":892,"line_start":29,"line_end":29,"column_start":9,"column_end":14},"ref_id":{"krate":0,"index":3690987527}},{"kind":"Variable","span":{"file_name":"src\\main.rs","byte_start":918,"byte_end":923,"line_start":31,"line_end":31,"column_start":9,"column_end":14},"ref_id":{"krate":0,"index":3690987527}},{"kind":"Variable","span":{"file_name":"src\\main.rs","byte_start":947,"byte_end":952,"line_start":33,"line_end":33,"column_start":12,"column_end":17},"ref_id":{"krate":0,"index":3690987527}},{"kind":"Variable","span":{"file_name":"src\\main.rs","byte_start":1040,"byte_end":1042,"line_start":37,"line_end":37,"column_start":21,"column_end":23},"ref_id":{"krate":0,"index":268435464}},{"kind":"Variable","span":{"file_name":"src\\main.rs","byte_start":1045,"byte_end":1047,"line_start":37,"line_end":37,"column_start":26,"column_end":28},"ref_id":{"krate":0,"index":536870920}},{"kind":"Variable","span":{"file_name":"src\\main.rs","byte_start":1069,"byte_end":1071,"line_start":38,"line_end":38,"column_start":21,"column_end":23},"ref_id":{"krate":0,"index":1610612744}},{"kind":"Variable","span":{"file_name":"src\\main.rs","byte_start":1074,"byte_end":1076,"line_start":38,"line_end":38,"column_start":26,"column_end":28},"ref_id":{"krate":0,"index":1073741832}},{"kind":"Variable","span":{"file_name":"src\\main.rs","byte_start":1111,"byte_end":1116,"line_start":39,"line_end":39,"column_start":34,"column_end":39},"ref_id":{"krate":0,"index":2281701384}},{"kind":"Variable","span":{"file_name":"src\\main.rs","byte_start":1119,"byte_end":1124,"line_start":39,"line_end":39,"column_start":42,"column_end":47},"ref_id":{"krate":0,"index":3623878664}},{"kind":"Type","span":{"file_name":"src\\main.rs","byte_start":1145,"byte_end":1151,"line_start":40,"line_end":40,"column_start":20,"column_end":26},"ref_id":{"krate":5,"index":7286}},{"kind":"Variable","span":{"file_name":"src\\main.rs","byte_start":1160,"byte_end":1178,"line_start":41,"line_end":41,"column_start":8,"column_end":26},"ref_id":{"krate":0,"index":2751463432}},{"kind":"Variable","span":{"file_name":"src\\main.rs","byte_start":1194,"byte_end":1199,"line_start":42,"line_end":42,"column_start":9,"column_end":14},"ref_id":{"krate":0,"index":1409286152}},{"kind":"Variable","span":{"file_name":"src\\main.rs","byte_start":1219,"byte_end":1237,"line_start":43,"line_end":43,"column_start":14,"column_end":32},"ref_id":{"krate":0,"index":2751463432}},{"kind":"Variable","span":{"file_name":"src\\main.rs","byte_start":1253,"byte_end":1258,"line_start":44,"line_end":44,"column_start":9,"column_end":14},"ref_id":{"krate":0,"index":1409286152}},{"kind":"Variable","span":{"file_name":"src\\main.rs","byte_start":1284,"byte_end":1289,"line_start":46,"line_end":46,"column_start":9,"column_end":14},"ref_id":{"krate":0,"index":1409286152}},{"kind":"Variable","span":{"file_name":"src\\main.rs","byte_start":1313,"byte_end":1318,"line_start":48,"line_end":48,"column_start":12,"column_end":17},"ref_id":{"krate":0,"index":1409286152}},{"kind":"Function","span":{"file_name":"src\\main.rs","byte_start":1410,"byte_end":1436,"line_start":52,"line_end":52,"column_start":35,"column_end":61},"ref_id":{"krate":0,"index":8}},{"kind":"Variable","span":{"file_name":"src\\main.rs","byte_start":1437,"byte_end":1439,"line_start":52,"line_end":52,"column_start":62,"column_end":64},"ref_id":{"krate":0,"index":1073741833}},{"kind":"Variable","span":{"file_name":"src\\main.rs","byte_start":1441,"byte_end":1443,"line_start":52,"line_end":52,"column_start":66,"column_end":68},"ref_id":{"krate":0,"index":536870921}},{"kind":"Variable","span":{"file_name":"src\\main.rs","byte_start":1445,"byte_end":1447,"line_start":52,"line_end":52,"column_start":70,"column_end":72},"ref_id":{"krate":0,"index":1610612745}},{"kind":"Variable","span":{"file_name":"src\\main.rs","byte_start":1449,"byte_end":1451,"line_start":52,"line_end":52,"column_start":74,"column_end":76},"ref_id":{"krate":0,"index":268435465}},{"kind":"Function","span":{"file_name":"src\\main.rs","byte_start":1487,"byte_end":1512,"line_start":53,"line_end":53,"column_start":34,"column_end":59},"ref_id":{"krate":0,"index":7}},{"kind":"Variable","span":{"file_name":"src\\main.rs","byte_start":1513,"byte_end":1515,"line_start":53,"line_end":53,"column_start":60,"column_end":62},"ref_id":{"krate":0,"index":1073741833}},{"kind":"Variable","span":{"file_name":"src\\main.rs","byte_start":1517,"byte_end":1519,"line_start":53,"line_end":53,"column_start":64,"column_end":66},"ref_id":{"krate":0,"index":536870921}},{"kind":"Variable","span":{"file_name":"src\\main.rs","byte_start":1521,"byte_end":1523,"line_start":53,"line_end":53,"column_start":68,"column_end":70},"ref_id":{"krate":0,"index":1610612745}},{"kind":"Variable","span":{"file_name":"src\\main.rs","byte_start":1525,"byte_end":1527,"line_start":53,"line_end":53,"column_start":72,"column_end":74},"ref_id":{"krate":0,"index":268435465}},{"kind":"Function","span":{"file_name":"src\\main.rs","byte_start":1665,"byte_end":1681,"line_start":61,"line_end":61,"column_start":33,"column_end":49},"ref_id":{"krate":0,"index":9}},{"kind":"Variable","span":{"file_name":"src\\main.rs","byte_start":1682,"byte_end":1684,"line_start":61,"line_end":61,"column_start":50,"column_end":52},"ref_id":{"krate":0,"index":2684354570}},{"kind":"Variable","span":{"file_name":"src\\main.rs","byte_start":1686,"byte_end":1688,"line_start":61,"line_end":61,"column_start":54,"column_end":56},"ref_id":{"krate":0,"index":3489660938}},{"kind":"Variable","span":{"file_name":"src\\main.rs","byte_start":1690,"byte_end":1692,"line_start":61,"line_end":61,"column_start":58,"column_end":60},"ref_id":{"krate":0,"index":2281701386}},{"kind":"Variable","span":{"file_name":"src\\main.rs","byte_start":1694,"byte_end":1696,"line_start":61,"line_end":61,"column_start":62,"column_end":64},"ref_id":{"krate":0,"index":3892314122}},{"kind":"Function","span":{"file_name":"src\\main.rs","byte_start":1731,"byte_end":1747,"line_start":62,"line_end":62,"column_start":33,"column_end":49},"ref_id":{"krate":0,"index":6}},{"kind":"Variable","span":{"file_name":"src\\main.rs","byte_start":1748,"byte_end":1750,"line_start":62,"line_end":62,"column_start":50,"column_end":52},"ref_id":{"krate":0,"index":2684354570}},{"kind":"Variable","span":{"file_name":"src\\main.rs","byte_start":1752,"byte_end":1754,"line_start":62,"line_end":62,"column_start":54,"column_end":56},"ref_id":{"krate":0,"index":3489660938}},{"kind":"Variable","span":{"file_name":"src\\main.rs","byte_start":1756,"byte_end":1758,"line_start":62,"line_end":62,"column_start":58,"column_end":60},"ref_id":{"krate":0,"index":2281701386}},{"kind":"Variable","span":{"file_name":"src\\main.rs","byte_start":1760,"byte_end":1762,"line_start":62,"line_end":62,"column_start":62,"column_end":64},"ref_id":{"krate":0,"index":3892314122}}],"macro_refs":[],"relations":[]}